[
  {
    "id": "1",
    "item": "202",
    "name": "Producto 1",
    "discountedPrice": 39000,
    "listPrice": 45000,
    "image": "/images/products/hoodie.jpg",
    "category": "buzos",
    "inStock": false,
    "sizes": [
      { "size": "S", "quantity": 1 },
      { "size": "M", "quantity": 1 },
      { "size": "L", "quantity": 1 },
      { "size": "XL", "quantity": 1 }
    ]
  },
  {
    "id": "2",
    "item": "202",
    "name": "Producto 2",
    "discountedPrice": 39000,
    "listPrice": 45000,
    "image": "/images/products/hoodie.webp",
    "category": "buzos",
    "inStock": true,
    "sizes": [
      { "size": "S", "quantity": 0 },
      { "size": "M", "quantity": 1 },
      { "size": "L", "quantity": 1 },
      { "size": "XL", "quantity": 1 }
    ]
  },
  {
    "id": "7",
    "item": "301",
    "name": "Producto 7",
    "discountedPrice": 35000,
    "listPrice": 43000, 
    "image": "/images/products/jeans.webp",
    "category": "pantalones",
    "inStock": true,
    "sizes": [
      { "size": "28", "quantity": 1 },
      { "size": "30", "quantity": 1 },
      { "size": "32", "quantity": 1 },
      { "size": "34", "quantity": 1 }
    ]
  },
  {
    "id": "8",
    "item": "301",
    "name": "Producto 8",
    "discountedPrice": 35000,
    "listPrice":43000,
    "image": "/images/products/pantalon.webp",
    "category": "pantalones",
    "inStock": true,
    "sizes": [
      { "size": "28", "quantity": 1 },
      { "size": "30", "quantity": 1 },
      { "size": "32", "quantity": 1 },
      { "size": "34", "quantity": 1 }
    ]
  },
  {
    "id": "9",
    "item": "301",
    "name": "Producto 9",
    "discountedPrice": 20000,
    "listPrice": 25000,
    "image": "/images/products/Jogging.webp",
    "category": "pantalones",
    "inStock": true,
    "sizes": [
      { "size": "S", "quantity": 1 },
      { "size": "M", "quantity": 1 },
      { "size": "L", "quantity": 1 },
      { "size": "XL", "quantity": 1 }
    ]
  },
  {
    "id": "10",
    "item": "502",
    "name": "Producto 10",
    "discountedPrice": 9900,
    "listPrice": 11900,
    "image": "/images/products/mini-bag.jpg",
    "category": "bags",
    "inStock": true,
    "sizes": [{"size": "unico", "quantity": 1}]
  },
  {
    "id": "11",
    "item": "502",
    "name": "Producto 11",
    "discountedPrice": 11900,
    "listPrice": 13900,
    "image": "/images/products/morral-gris.jpg",
    "category": "bags",
    "inStock": true,
    "sizes": [{"size": "unico", "quantity": 1}]
  },
  {
    "id": "12",
    "item": "502",
    "name": "Producto 12",
    "discountedPrice": 11900,
    "listPrice": 13900,
    "image": "/images/products/morral-negro-red.jpg",
    "category": "bags",
    "inStock": true,
    "sizes": [{"size": "unico", "quantity": 1}]
  },
  {
    "id": "13",
    "item": "001",
    "name": "Producto 13",
    "discountedPrice": 4900,
    "listPrice":5999,
    "image": "/images/products/boxer.jpg",
    "category": "accesorios",
    "inStock": true,
    "sizes": [
      { "size": "S", "quantity": 1 },
      { "size": "M", "quantity": 1 },
      { "size": "L", "quantity": 1 },
      { "size": "XL", "quantity": 1 }
    ]
  },
  {
    "id": "14",
    "item": "001",
    "name": "Producto 14",
    "discountedPrice": 3900,
    "listPrice": 4950,
    "image": "/images/products/gorra.jpg",
    "category": "accesorios",
    "inStock": true,
    "sizes": [{"size": "unico", "quantity": 1}]
  },
  {
    "id": "15",
    "item": "002",
    "name": "Producto 15",
    "discountedPrice": 2900,
    "listPrice": 3500,
    "image": "/images/products/medias-2.jpg",
    "category": "accesorios",
    "inStock": true,
    "sizes": [{"size": "unico", "quantity": 1}]
  },
  {
    "id": "16",
    "item": "202",
    "name": "Producto 16",
    "discountedPrice": 39000,
    "listPrice": 45000,
    "image": "/images/products/modelo-buzo-gris-sm.jpg",
    "category": "buzos",
    "inStock": true,
    "sizes": [
      { "size": "S", "quantity": 1 },
      { "size": "M", "quantity": 1 },
      { "size": "L", "quantity": 1 },
      { "size": "XL", "quantity": 1 }
    ]
  },
  {
    "id": "art-remera-mc-gris-basix",
    "item": "1011",
    "name": "Remera MC Gris Basix",
    "discountedPrice": 6900,
    "listPrice": 7999,
    "image": "/images/products/remera-gris.jpg",
    "category": "remeras",
    "inStock": false,
    "sizes": [
      { "size": "S", "quantity": 1 },
      { "size": "M", "quantity": 1 },
      { "size": "L", "quantity": 1 },
      { "size": "XL", "quantity": 1 }
    ]
  },
  {
    "id": "art-remera-mc-negra-basix",
    "item": "1011",
    "name": "Remera MC Negra Basix",
    "discountedPrice": 6900,
    "listPrice": 7999,
    "image": "/images/products/remera-negra.jpg",
    "category": "remeras",
    "inStock": true,
    "sizes": [
      { "size": "S", "quantity": 1 },
      { "size": "M", "quantity": 1 },
      { "size": "L", "quantity": 1 },
      { "size": "XL", "quantity": 1 }
    ]
  },
  {
    "id": "art-remeraMC-blanca-APV",
    "item": "1012",
    "name": "Remera MC Blanca Elevé",
    "discountedPrice": 9900,
    "listPrice": 11900,
    "image": "/images/products/algodonera/remera-mc-algodonera-blanca.jpg",
    "category": "remeras",
    "inStock": true,
    "sizes": [
      { "size": "S", "quantity": 1 },
      { "size": "M", "quantity": 1 },
      { "size": "L", "quantity": 1 },
      { "size": "XL", "quantity": 1 }
    ]
  },
  {
    "id": "art-remeraMC-gris-APV",
    "item": "1012",
    "name": "Remera MC Gris Elevé",
    "discountedPrice": 9900,
    "listPrice": 11900,
    "image": "/images/products/algodonera/remera-mc-algodonera-gris.jpg",
    "category": "remeras",
    "inStock": true,
    "sizes": [
      { "size": "S", "quantity": 1 },
      { "size": "M", "quantity": 1 },
      { "size": "L", "quantity": 1 },
      { "size": "XL", "quantity": 1 }
    ]
  },
  {
    "id": "art-remeraMC-azulmarino-APV",
    "item": "1012",
    "name": "Remera MC Azul Elevé",
    "discountedPrice": 9900,
    "listPrice": 11900,
    "image": "/images/products/algodonera/remera-mc-algodonera-azul.jpg",
    "category": "remeras",
    "inStock": true,
    "sizes": [
      { "size": "S", "quantity": 1 },
      { "size": "M", "quantity": 1 },
      { "size": "L", "quantity": 1 },
      { "size": "XL", "quantity": 1 }
    ]
  },
  {
    "id": "art-remeraMC-negro-APV",
    "item": "1012",
    "name": "Remera MC Negra Elevé",
    "discountedPrice": 9900,
    "listPrice": 11900,
    "image": "/images/products/algodonera/remera-mc-algodonera-negra.jpg",
    "category": "remeras",
    "inStock": true,
    "sizes": [
      { "size": "S", "quantity": 1 },
      { "size": "M", "quantity": 1 },
      { "size": "L", "quantity": 1 },
      { "size": "XL", "quantity": 1 }
    ]
  },
  {
    "id": "art-remeraMC-batik-azul-APV",
    "item": "1013",
    "name": "Remera MC Azul Batik",
    "discountedPrice": 10900,
    "listPrice": 13900,
    "image": "/images/products/algodonera/remera-mc-batik-algodonera-azul.jpg",
    "category": "remeras",
    "inStock": true,
    "sizes": [
      { "size": "S", "quantity": 1 },
      { "size": "M", "quantity": 1 },
      { "size": "L", "quantity": 1 },
      { "size": "XL", "quantity": 1 }
    ]
  },
  {
    "id": "art-remeraMC-batik-verde-APV",
    "item": "1013",
    "name": "Remera MC Verde Batik",
    "discountedPrice": 10900,
    "listPrice": 13900,
    "image": "/images/products/algodonera/remera-mc-batik-algodonera-verde.jpg",
    "category": "remeras",
    "inStock": true,
    "sizes": [
      { "size": "S", "quantity": 0 },
      { "size": "M", "quantity": 1 },
      { "size": "L", "quantity": 1 },
      { "size": "XL", "quantity": 1 }
    ]
  }
]